{"cameraMode":{"drawMode":0,"name":"Shaded","section":"Shading Mode"},"sceneLighting":true,"audioPlay":false,"sceneViewState":{"m_AlwaysRefresh":false,"showFog":true,"showSkybox":true,"showFlares":true,"showImageEffects":true,"showParticleSystems":true,"showVisualEffectGraphs":true,"m_FxEnabled":true},"in2DMode":false,"pivot":{"x":2.718074321746826,"y":3.029860734939575,"z":24.58582305908203},"rotation":{"x":0.01827527955174446,"y":-0.08641290664672852,"z":0.0012221713550388814,"w":0.9960954785346985},"size":4.2047119140625,"orthographic":false}